streamforge/__init__.py
streamforge/binance_test.py
streamforge/kraken_test.py
streamforge/merge_stream.py
streamforge/polygon_test.py
streamforge/py.typed
streamforge/runners_test.py
streamforge/base/__init__.py
streamforge/base/api.py
streamforge/base/exchange.py
streamforge/base/models.py
streamforge/base/runner.py
streamforge/base/stream_input.py
streamforge/base/ws.py
streamforge/base/data_container/__init__.py
streamforge/base/data_container/ohlc.py
streamforge/base/data_container/util.py
streamforge/base/data_processor/__init__.py
streamforge/base/data_processor/aggregate.py
streamforge/base/data_processor/ohlc.py
streamforge/base/data_processor/processor.py
streamforge/base/emitters/__init__.py
streamforge/base/emitters/base.py
streamforge/base/emitters/mapper.py
streamforge/base/emitters/util.py
streamforge/base/emitters/csv/__init__.py
streamforge/base/emitters/csv/csv.py
streamforge/base/emitters/kafka/__init__.py
streamforge/base/emitters/kafka/kafka.py
streamforge/base/emitters/logger/__init__.py
streamforge/base/emitters/logger/logger.py
streamforge/base/emitters/postgresql/__init__.py
streamforge/base/emitters/postgresql/db.py
streamforge/base/emitters/postgresql/models.py
streamforge/base/normalize/__init__.py
streamforge/base/normalize/normalize.py
streamforge/base/normalize/ohlc/__init__.py
streamforge/base/normalize/ohlc/maps.py
streamforge/base/normalize/ohlc/processor.py
streamforge/base/normalize/ohlc/util.py
streamforge/base/normalize/ohlc/api/__init__.py
streamforge/base/normalize/ohlc/api/binance.py
streamforge/base/normalize/ohlc/api/kraken.py
streamforge/base/normalize/ohlc/models/__init__.py
streamforge/base/normalize/ohlc/models/candle.py
streamforge/base/normalize/ohlc/models/normalizer.py
streamforge/base/normalize/ohlc/models/timeframes.py
streamforge/ingestion/__init__.py
streamforge/ingestion/binance/__init__.py
streamforge/ingestion/binance/backfilling.py
streamforge/ingestion/binance/runner.py
streamforge-0.1.1.dist-info/licenses/LICENSE
streamforge-0.1.1.dist-info/METADATA
streamforge-0.1.1.dist-info/WHEEL
streamforge-0.1.1.dist-info/top_level.txt
streamforge-0.1.1.dist-info/RECORD
