Metadata-Version: 2.4
Name: streamforge
Version: 0.1.1
Summary: Real-time cryptocurrency and financial data ingestion system
Home-page: https://github.com/paulobueno90/streamforge
Author: Paulo Bueno
Author-email: Paulo Bueno <paulohmbueno@gmail.com>
Maintainer-email: Paulo Bueno <paulohmbueno@gmail.com>
License: MIT
Project-URL: Homepage, https://github.com/paulobueno90/streamforge
Project-URL: Documentation, https://paulobueno90.github.io/streamforge/
Project-URL: Repository, https://github.com/paulobueno90/streamforge
Project-URL: Bug Tracker, https://github.com/paulobueno90/streamforge/issues
Project-URL: Changelog, https://github.com/paulobueno90/streamforge/blob/main/CHANGELOG.md
Keywords: cryptocurrency,crypto,stocks,options,trading,data,ingestion,websocket,binance,kraken,okx,streamforge,real-time,market-data
Classifier: Development Status :: 3 - Alpha
Classifier: Intended Audience :: Developers
Classifier: Intended Audience :: Financial and Insurance Industry
Classifier: License :: OSI Approved :: MIT License
Classifier: Operating System :: OS Independent
Classifier: Programming Language :: Python :: 3
Classifier: Programming Language :: Python :: 3.8
Classifier: Programming Language :: Python :: 3.9
Classifier: Programming Language :: Python :: 3.10
Classifier: Programming Language :: Python :: 3.11
Classifier: Programming Language :: Python :: 3.12
Classifier: Topic :: Software Development :: Libraries :: Python Modules
Classifier: Topic :: Office/Business :: Financial
Classifier: Topic :: Office/Business :: Financial :: Investment
Classifier: Typing :: Typed
Requires-Python: >=3.8
License-File: LICENSE
Requires-Dist: aiohttp>=3.8.0
Requires-Dist: websockets>=10.0
Requires-Dist: sqlalchemy>=1.4.0
Requires-Dist: pandas>=1.3.0
Requires-Dist: pydantic>=1.8.0
Requires-Dist: orjson>=3.6.0
Requires-Dist: aiokafka>=0.8.0
Requires-Dist: asyncpg>=0.27.0
Requires-Dist: aiolimiter>=1.1.0
Requires-Dist: python-dateutil>=2.8.0
Requires-Dist: numpy>=1.20.0
Requires-Dist: requests>=2.25.0
Requires-Dist: ciso8601>=2.2.0
Provides-Extra: dev
Requires-Dist: pytest>=6.0; extra == "dev"
Requires-Dist: pytest-asyncio>=0.18.0; extra == "dev"
Requires-Dist: pytest-cov>=3.0.0; extra == "dev"
Requires-Dist: black>=21.0.0; extra == "dev"
Requires-Dist: flake8>=3.8.0; extra == "dev"
Requires-Dist: mypy>=0.800; extra == "dev"
Requires-Dist: isort>=5.0.0; extra == "dev"
Provides-Extra: test
Requires-Dist: pytest>=6.0; extra == "test"
Requires-Dist: pytest-asyncio>=0.18.0; extra == "test"
Requires-Dist: pytest-cov>=3.0.0; extra == "test"
Provides-Extra: docs
Requires-Dist: mkdocs>=1.5.0; extra == "docs"
Requires-Dist: mkdocs-material>=9.5.0; extra == "docs"
Requires-Dist: mkdocstrings[python]>=0.24.0; extra == "docs"
Requires-Dist: pymdown-extensions>=10.0; extra == "docs"
Dynamic: author
Dynamic: home-page
Dynamic: license-file
Dynamic: requires-python
